ObjectListView2/CellEditor.py
ObjectListView2/Filter.py
ObjectListView2/ListCtrlPrinter.py
ObjectListView2/OLVEvent.py
ObjectListView2/OLVPrinter.py
ObjectListView2/ObjectListView.py
ObjectListView2/WordWrapRenderer.py
ObjectListView2/__init__.py
ObjectListView2-1.0.1.dist-info/AUTHORS.txt
ObjectListView2-1.0.1.dist-info/LICENSE.txt
ObjectListView2-1.0.1.dist-info/METADATA
ObjectListView2-1.0.1.dist-info/WHEEL
ObjectListView2-1.0.1.dist-info/top_level.txt
ObjectListView2-1.0.1.dist-info/RECORD
