Metadata-Version: 2.1
Name: ObjectListView2
Version: 1.0.1
Summary: An ObjectListView is a wrapper around the wx.ListCtrl that makes the list control easier to use. This is an upload of olv 1.3.2 from https://bitbucket.org/wbruhin/objectlistview/
Home-page: https://github.com/eriknystrom/ObjectListView2
Author: Phillip Piper
Author-email: phillip.piper@gmail.com
Maintainer: Erik Nystrom
Maintainer-email: Erik.Nystrom87@gmail.com
License: wxWindows
Download-URL: https://github.com/eriknystrom/ObjectListView2/releases
Platform: Many
Classifier: Development Status :: 4 - Beta
Classifier: Intended Audience :: Developers
Classifier: Topic :: Software Development :: User Interfaces
